spoon_server/__init__.py
spoon_server/browser/__init__.py
spoon_server/browser/webdriver_item.py
spoon_server/browser/webdriver_pool.py
spoon_server/browser/webdriver_pool_config.py
spoon_server/database/__init__.py
spoon_server/database/redis_config.py
spoon_server/database/redis_wrapper.py
spoon_server/example/__init__.py
spoon_server/example/example.py
spoon_server/example/example_multi.py
spoon_server/example/provider_availble.py
spoon_server/main/__init__.py
spoon_server/main/checker.py
spoon_server/main/manager.py
spoon_server/main/proxy_pipe.py
spoon_server/main/refresher.py
spoon_server/main/validater.py
spoon_server/proxy/__init__.py
spoon_server/proxy/busy_provider.py
spoon_server/proxy/cool_provider.py
spoon_server/proxy/feilong_provider.py
spoon_server/proxy/fetcher.py
spoon_server/proxy/file_provider.py
spoon_server/proxy/fpl_provider.py
spoon_server/proxy/gou_provider.py
spoon_server/proxy/gp_provider.py
spoon_server/proxy/ihuan_provider.py
spoon_server/proxy/ip181_provider.py
spoon_server/proxy/ip31_provider.py
spoon_server/proxy/ip3366_provider.py
spoon_server/proxy/iphai_provider.py
spoon_server/proxy/kuai_provider.py
spoon_server/proxy/listende_provider.py
spoon_server/proxy/mipu_provider.py
spoon_server/proxy/nian_provider.py
spoon_server/proxy/nntime_provider.py
spoon_server/proxy/nord_provider.py
spoon_server/proxy/pdb_provider.py
spoon_server/proxy/plp_provider.py
spoon_server/proxy/prem_provider.py
spoon_server/proxy/provider.py
spoon_server/proxy/six_provider.py
spoon_server/proxy/ssl_provider.py
spoon_server/proxy/us_provider.py
spoon_server/proxy/web_provider.py
spoon_server/proxy/wuyou_provider.py
spoon_server/proxy/xiaohexia_provider.py
spoon_server/proxy/xici_provider.py
spoon_server/proxy/xun_provider.py
spoon_server/proxy/yao_provider.py
spoon_server/proxy/you_provider.py
spoon_server/proxy/zdaye_provider.py
spoon_server/util/__init__.py
spoon_server/util/captcha.py
spoonproxy-0.3.2.dist-info/DESCRIPTION.rst
spoonproxy-0.3.2.dist-info/METADATA
spoonproxy-0.3.2.dist-info/RECORD
spoonproxy-0.3.2.dist-info/WHEEL
spoonproxy-0.3.2.dist-info/metadata.json
spoonproxy-0.3.2.dist-info/top_level.txt
