Metadata-Version: 2.0
Name: spoonproxy
Version: 0.3.2
Summary: A package for building specific Proxy Pool for different Sites.
Home-page: https://github.com/Jiramew/spoon
Author: Jiramew
Author-email: hanbingflying@sina.com
License: BSD License
Platform: all
Classifier: Development Status :: 3 - Alpha
Classifier: License :: OSI Approved :: BSD License
Classifier: Programming Language :: Python
Classifier: Programming Language :: Python :: 3
Classifier: Programming Language :: Python :: 3.6
Classifier: Topic :: Software Development :: Libraries
Requires-Dist: PyExecJS (>=1.4.0)
Requires-Dist: lxml (>=3.8.0)
Requires-Dist: redis (>=2.10.5)
Requires-Dist: requests (>=2.18.1)
Requires-Dist: schedule (>=0.4.3)
